tcoi/__init__.py
tcoi/classes.py
tcoi/errors.py
tcoi-0.2.5.dist-info/LICENSE
tcoi-0.2.5.dist-info/METADATA
tcoi-0.2.5.dist-info/WHEEL
tcoi-0.2.5.dist-info/top_level.txt
tcoi-0.2.5.dist-info/RECORD
