Metadata-Version: 2.1
Name: tcoi
Version: 0.2.5
Summary: A New Form of Decentralised Hashing.
Author-email: Husayn Haras <husayn@dnmx.org>
Project-URL: Homepage, https://qurashiakh.dev/the-code-of-ishaq.html
Project-URL: Bug Tracker, https://github.com/hharas/tcoi/issues
Classifier: Programming Language :: Python :: 3
Classifier: License :: OSI Approved :: GNU General Public License v3 (GPLv3)
Classifier: Topic :: Utilities
Classifier: Operating System :: OS Independent
Requires-Python: >=3.7
License-File: LICENSE
